random_permutation/__init__.py
random_permutation/permutation.py
random_permutation-0.1.15.dist-info/LICENSE
random_permutation-0.1.15.dist-info/METADATA
random_permutation-0.1.15.dist-info/WHEEL
random_permutation-0.1.15.dist-info/top_level.txt
random_permutation-0.1.15.dist-info/RECORD
