Metadata-Version: 2.1
Name: random-permutation
Version: 0.1.15
Summary: A module for efficiently generating very large random permutations
Author: Gary William Flake
Author-email: gary@flake.org
Classifier: Programming Language :: Python :: 3
Classifier: License :: OSI Approved :: MIT License
Classifier: Operating System :: OS Independent
License-File: LICENSE
Requires-Dist: cryptography
